{"title":"Survivor S26E14 HDTV x264-2HD [eztv]","uid":8468501,"size":885589560,"categoryP":"video","categoryS":"tv_shows","magnet":"?xt=urn:btih:16ab04cec3960d538ab876e7e30efe162cb76632&amp;dn=Survivor+S26E14+HDTV+x264-2HD+%5Beztv%5D&amp;tr=udp%3A%2F%2Ftracker.openbittorrent.com%3A80&amp;tr=udp%3A%2F%2Fopen.demonii.com%3A1337&amp;tr=udp%3A%2F%2Ftracker.coppersurfer.tk%3A6969&amp;tr=udp%3A%2F%2Fexodus.desync.com%3A6969","seeders":1,"leechers":0,"uploader":"eztv","files":1,"time":1368421424,"description":"Help us by donating with BitCoin: 1Fw4sRdZYFwULfeE7oQ91GLYKy8j5EcuFW\n\n#EZTV @ EFNet -&gt; To avoid fakes, ALWAYS check that the torrent was added by eztv. &lt;a href=&quot;\nhttp://eztv.it/&quot; rel=&quot;nofollow&quot; target=&quot;_NEW&quot;&gt;\nhttp://eztv.it/&lt;/a&gt;\n\nEpisode: Survivor S26E14 HDTV x264-2HD\nScreenshots:\n\n\n","torrent":{"xt":"urn:btih:16ab04cec3960d538ab876e7e30efe162cb76632","amp;dn":"Survivor+S26E14+HDTV+x264-2HD+%5Beztv%5D","amp;tr":["udp%3A%2F%2Ftracker.openbittorrent.com%3A80","udp%3A%2F%2Fopen.demonii.com%3A1337","udp%3A%2F%2Ftracker.coppersurfer.tk%3A6969","udp%3A%2F%2Fexodus.desync.com%3A6969"],"infoHash":"16ab04cec3960d538ab876e7e30efe162cb76632","infoHashBuffer":{"type":"Buffer","data":[22,171,4,206,195,150,13,83,138,184,118,231,227,14,254,22,44,183,102,50]},"announce":[],"urlList":[]}}