{"title":"Naruto Shippuden Complete S01-S13 (Ep1-Ep307) 720p","uid":8341788,"size":15326321962,"categoryP":"video","categoryS":"hd___tv_shows","magnet":"?xt=urn:btih:26020c5ba6c3747111b604e1014eb09cd980ad53&amp;dn=Naruto+Shippuden+Complete+S01-S13+%28Ep1-Ep307%29+720p&amp;tr=udp%3A%2F%2Ftracker.openbittorrent.com%3A80&amp;tr=udp%3A%2F%2Fopen.demonii.com%3A1337&amp;tr=udp%3A%2F%2Ftracker.coppersurfer.tk%3A6969&amp;tr=udp%3A%2F%2Fexodus.desync.com%3A6969","seeders":1,"leechers":7,"uploader":"bluto278","files":288,"time":1365110377,"description":"This the complete series of naruto shippuden Updated Mostly 720p","torrent":{"xt":"urn:btih:26020c5ba6c3747111b604e1014eb09cd980ad53","amp;dn":"Naruto+Shippuden+Complete+S01-S13+%28Ep1-Ep307%29+720p","amp;tr":["udp%3A%2F%2Ftracker.openbittorrent.com%3A80","udp%3A%2F%2Fopen.demonii.com%3A1337","udp%3A%2F%2Ftracker.coppersurfer.tk%3A6969","udp%3A%2F%2Fexodus.desync.com%3A6969"],"infoHash":"26020c5ba6c3747111b604e1014eb09cd980ad53","infoHashBuffer":{"type":"Buffer","data":[38,2,12,91,166,195,116,113,17,182,4,225,1,78,176,156,217,128,173,83]},"announce":[],"urlList":[]}}