{"title":"Love.Thy.Neighbor.2013.S01E19.720p.HDTV.x264-EVOLVE","uid":8765720,"size":549239414,"categoryP":"video","categoryS":"hd___tv_shows","magnet":"?xt=urn:btih:3026bd633ca50ef6f34374529f5a56997fd4941a&amp;dn=Love.Thy.Neighbor.2013.S01E19.720p.HDTV.x264-EVOLVE&amp;tr=udp%3A%2F%2Ftracker.openbittorrent.com%3A80&amp;tr=udp%3A%2F%2Fopen.demonii.com%3A1337&amp;tr=udp%3A%2F%2Ftracker.coppersurfer.tk%3A6969&amp;tr=udp%3A%2F%2Fexodus.desync.com%3A6969","seeders":1,"leechers":0,"uploader":"TvTeam","files":5,"time":1375328598,"description":"::::::::::::::::::::::::::::::::::::::::::::::::::::::::::::::::::::::::::\n   &lt;a href=&quot;\nhttp://www.torrenting.com&quot; rel=&quot;nofollow&quot; target=&quot;_NEW&quot;&gt;\nhttp://www.torrenting.com&lt;/a&gt;\n\n::::::::::::::::::::::::::::::::::::::::::::::::::::::::::::::::::::::::::\n\n(= Enjoy No RAR releases =)","torrent":{"xt":"urn:btih:3026bd633ca50ef6f34374529f5a56997fd4941a","amp;dn":"Love.Thy.Neighbor.2013.S01E19.720p.HDTV.x264-EVOLVE","amp;tr":["udp%3A%2F%2Ftracker.openbittorrent.com%3A80","udp%3A%2F%2Fopen.demonii.com%3A1337","udp%3A%2F%2Ftracker.coppersurfer.tk%3A6969","udp%3A%2F%2Fexodus.desync.com%3A6969"],"infoHash":"3026bd633ca50ef6f34374529f5a56997fd4941a","infoHashBuffer":{"type":"Buffer","data":[48,38,189,99,60,165,14,246,243,67,116,82,159,90,86,153,127,212,148,26]},"announce":[],"urlList":[]}}