{"title":"Diario AS  01.11.14","uid":11343641,"size":65443133,"categoryP":"other","categoryS":"other","magnet":"?xt=urn:btih:46726900de4f01a5dc2fcfb0ddad1ec39672218e&amp;dn=Diario+AS++01.11.14&amp;tr=udp%3A%2F%2Ftracker.openbittorrent.com%3A80&amp;tr=udp%3A%2F%2Fopen.demonii.com%3A1337&amp;tr=udp%3A%2F%2Ftracker.coppersurfer.tk%3A6969&amp;tr=udp%3A%2F%2Fexodus.desync.com%3A6969","seeders":1,"leechers":0,"uploader":"virana","files":2,"time":1414825339,"description":"as","torrent":{"xt":"urn:btih:46726900de4f01a5dc2fcfb0ddad1ec39672218e","amp;dn":"Diario+AS++01.11.14","amp;tr":["udp%3A%2F%2Ftracker.openbittorrent.com%3A80","udp%3A%2F%2Fopen.demonii.com%3A1337","udp%3A%2F%2Ftracker.coppersurfer.tk%3A6969","udp%3A%2F%2Fexodus.desync.com%3A6969"],"infoHash":"46726900de4f01a5dc2fcfb0ddad1ec39672218e","infoHashBuffer":{"type":"Buffer","data":[70,114,105,0,222,79,1,165,220,47,207,176,221,173,30,195,150,114,33,142]},"announce":[],"urlList":[]}}