{"title":"Metalocalypse S02E12 Revengencers x264 HDTV","uid":4268823,"size":172583902,"categoryP":"video","categoryS":"hd___tv_shows","magnet":"?xt=urn:btih:47a88f265f55eeeb3af8536381c7993f4cd368f5&amp;dn=Metalocalypse+S02E12+Revengencers+x264+HDTV&amp;tr=udp%3A%2F%2Ftracker.openbittorrent.com%3A80&amp;tr=udp%3A%2F%2Fopen.demonii.com%3A1337&amp;tr=udp%3A%2F%2Ftracker.coppersurfer.tk%3A6969&amp;tr=udp%3A%2F%2Fexodus.desync.com%3A6969","seeders":1,"leechers":1,"uploader":"circlensess","files":2,"time":1214841839,"description":"metalocalypse x264 AC3 5.1\nS02E12 Revengencers\nx264 1700k\nAC3 5.1 384k\n768x432","torrent":{"xt":"urn:btih:47a88f265f55eeeb3af8536381c7993f4cd368f5","amp;dn":"Metalocalypse+S02E12+Revengencers+x264+HDTV","amp;tr":["udp%3A%2F%2Ftracker.openbittorrent.com%3A80","udp%3A%2F%2Fopen.demonii.com%3A1337","udp%3A%2F%2Ftracker.coppersurfer.tk%3A6969","udp%3A%2F%2Fexodus.desync.com%3A6969"],"infoHash":"47a88f265f55eeeb3af8536381c7993f4cd368f5","infoHashBuffer":{"type":"Buffer","data":[71,168,143,38,95,85,238,235,58,248,83,99,129,199,153,63,76,211,104,245]},"announce":[],"urlList":[]}}