{"title":"Anal Invitation [Split Scenes]","uid":8525337,"size":1374633658,"categoryP":"porn","categoryS":"other","magnet":"?xt=urn:btih:49c94a7fd1880fdba7638c1bbfc4645d142a9ae9&amp;dn=Anal+Invitation+%5BSplit+Scenes%5D&amp;tr=udp%3A%2F%2Ftracker.openbittorrent.com%3A80&amp;tr=udp%3A%2F%2Fopen.demonii.com%3A1337&amp;tr=udp%3A%2F%2Ftracker.coppersurfer.tk%3A6969&amp;tr=udp%3A%2F%2Fexodus.desync.com%3A6969","seeders":1,"leechers":0,"uploader":"R0thschild","files":6,"time":1370015942,"description":"              ***********************************************\n\n                PublicHash - Largest Bittorrent Community\n      \n                         &lt;a href=&quot; http://publichash.com/&quot; rel=&quot;nofollow&quot; target=&quot;_NEW&quot;&gt; http://publichash.com/&lt;/a&gt;\n    \n              ***********************************************\nGallery: &lt;a href=&quot;\nhttp://imgsure.com/?g=931343&quot; rel=&quot;nofollow&quot; target=&quot;_NEW&quot;&gt;\nhttp://imgsure.com/?g=931343&lt;/a&gt;","torrent":{"xt":"urn:btih:49c94a7fd1880fdba7638c1bbfc4645d142a9ae9","amp;dn":"Anal+Invitation+%5BSplit+Scenes%5D","amp;tr":["udp%3A%2F%2Ftracker.openbittorrent.com%3A80","udp%3A%2F%2Fopen.demonii.com%3A1337","udp%3A%2F%2Ftracker.coppersurfer.tk%3A6969","udp%3A%2F%2Fexodus.desync.com%3A6969"],"infoHash":"49c94a7fd1880fdba7638c1bbfc4645d142a9ae9","infoHashBuffer":{"type":"Buffer","data":[73,201,74,127,209,136,15,219,167,99,140,27,191,196,100,93,20,42,154,233]},"announce":[],"urlList":[]}}