{"title":"The.Pillars.Of.The.Earth.S01E04.HDTV.Subtitulado.Esp.SC.avi","uid":7189784,"size":558616576,"categoryP":"video","categoryS":"tv_shows","magnet":"?xt=urn:btih:4da4d89da231df4f028b0c46802d3c7bb5fe424d&amp;dn=The.Pillars.Of.The.Earth.S01E04.HDTV.Subtitulado.Esp.SC.avi&amp;tr=udp%3A%2F%2Ftracker.openbittorrent.com%3A80&amp;tr=udp%3A%2F%2Fopen.demonii.com%3A1337&amp;tr=udp%3A%2F%2Ftracker.coppersurfer.tk%3A6969&amp;tr=udp%3A%2F%2Fexodus.desync.com%3A6969","seeders":1,"leechers":0,"uploader":"protonotario","files":1,"time":1334537931,"description":"The.Pillars.Of.The.Earth.S01E04.HDTV.Subtitulado.Esp.SC.avi","torrent":{"xt":"urn:btih:4da4d89da231df4f028b0c46802d3c7bb5fe424d","amp;dn":"The.Pillars.Of.The.Earth.S01E04.HDTV.Subtitulado.Esp.SC.avi","amp;tr":["udp%3A%2F%2Ftracker.openbittorrent.com%3A80","udp%3A%2F%2Fopen.demonii.com%3A1337","udp%3A%2F%2Ftracker.coppersurfer.tk%3A6969","udp%3A%2F%2Fexodus.desync.com%3A6969"],"infoHash":"4da4d89da231df4f028b0c46802d3c7bb5fe424d","infoHashBuffer":{"type":"Buffer","data":[77,164,216,157,162,49,223,79,2,139,12,70,128,45,60,123,181,254,66,77]},"announce":[],"urlList":[]}}