{"title":"Chennaieil Oru Naal (2013) Tamil 1CD TC Rip XviD MP3 - MTR","uid":8327196,"size":743657376,"categoryP":"video","categoryS":"movies","magnet":"?xt=urn:btih:566671dc56d04ae519c7265c19c5e5d6a3f11298&amp;dn=Chennaieil+Oru+Naal+%282013%29+Tamil+1CD+TC+Rip+XviD+MP3+-+MTR&amp;tr=udp%3A%2F%2Ftracker.openbittorrent.com%3A80&amp;tr=udp%3A%2F%2Fopen.demonii.com%3A1337&amp;tr=udp%3A%2F%2Ftracker.coppersurfer.tk%3A6969&amp;tr=udp%3A%2F%2Fexodus.desync.com%3A6969","seeders":1,"leechers":0,"uploader":"HDvideos","files":2,"time":1364821675,"description":"mastitorrents.com\n  &lt;a href=&quot;\nhttp://mastitorrents.com/forums/index.php&quot; rel=&quot;nofollow&quot; target=&quot;_NEW&quot;&gt;\nhttp://mastitorrents.com/forums/index.php&lt;/a&gt;\n  &lt;a href=&quot;\nhttp://thepiratebay.se/user/HDvideos/0/7&quot; rel=&quot;nofollow&quot; target=&quot;_NEW&quot;&gt;\nhttp://thepiratebay.se/user/HDvideos/0/7&lt;/a&gt;\n\nChennaieil Oru Naal (2013) Tamil 1CD TC Rip XviD MP3 - MTR\n\nScreens: &lt;a href=&quot;\nhttp://i.imgur.com/AyWei9F.png&quot; rel=&quot;nofollow&quot; target=&quot;_NEW&quot;&gt;\nhttp://i.imgur.com/AyWei9F.png&lt;/a&gt; &lt;a href=&quot;\nhttp://i.imgur.com/4Xmw560.png&quot; rel=&quot;nofollow&quot; target=&quot;_NEW&quot;&gt;\nhttp://i.imgur.com/4Xmw560.png&lt;/a&gt; &lt;a href=&quot;\nhttp://i.imgur.com/z6U5EnF.png&quot; rel=&quot;nofollow&quot; target=&quot;_NEW&quot;&gt;\nhttp://i.imgur.com/z6U5EnF.png&lt;/a&gt; &lt;a href=&quot;\nhttp://i.imgur.com/sOGBJP7.png&quot; rel=&quot;nofollow&quot; target=&quot;_NEW&quot;&gt;\nhttp://i.imgur.com/sOGBJP7.png&lt;/a&gt; &lt;a href=&quot;\nhttp://i.imgur.com/cMMSCq0.png&quot; rel=&quot;nofollow&quot; target=&quot;_NEW&quot;&gt;\nhttp://i.imgur.com/cMMSCq0.png&lt;/a&gt;","torrent":{"xt":"urn:btih:566671dc56d04ae519c7265c19c5e5d6a3f11298","amp;dn":"Chennaieil+Oru+Naal+%282013%29+Tamil+1CD+TC+Rip+XviD+MP3+-+MTR","amp;tr":["udp%3A%2F%2Ftracker.openbittorrent.com%3A80","udp%3A%2F%2Fopen.demonii.com%3A1337","udp%3A%2F%2Ftracker.coppersurfer.tk%3A6969","udp%3A%2F%2Fexodus.desync.com%3A6969"],"infoHash":"566671dc56d04ae519c7265c19c5e5d6a3f11298","infoHashBuffer":{"type":"Buffer","data":[86,102,113,220,86,208,74,229,25,199,38,92,25,197,229,214,163,241,18,152]},"announce":[],"urlList":[]}}