{"title":"[PS3] CFW 4.50 v1.00-FERROX","uid":9027861,"size":209816681,"categoryP":"games","categoryS":"psx","magnet":"?xt=urn:btih:5b27f76967b84f0a3d0528a2d1dd0738c8310cf2&amp;dn=%5BPS3%5D+CFW+4.50+v1.00-FERROX&amp;tr=udp%3A%2F%2Ftracker.openbittorrent.com%3A80&amp;tr=udp%3A%2F%2Fopen.demonii.com%3A1337&amp;tr=udp%3A%2F%2Ftracker.coppersurfer.tk%3A6969&amp;tr=udp%3A%2F%2Fexodus.desync.com%3A6969","seeders":1,"leechers":0,"uploader":"Mno74","files":11,"time":1381397624,"description":"Here is a new Custom Firmware release for v4.50, following the previous releases from RazorX (PS3ultimate 4.50) &amp; smhabib (Habib v4.50). This time around PS3 Developer Alexander known for his previous CFW releases and his Unofficial Fork of Iris Manager., has now released his latest CFW version. With his release of FERROX: 4.50 CFW v1.0, This CFW comes with alot of the usual patches and then some extras like the recent XMB Screenshot Patches that we reported recently and various other features you can see in the list from the Release ","torrent":{"xt":"urn:btih:5b27f76967b84f0a3d0528a2d1dd0738c8310cf2","amp;dn":"%5BPS3%5D+CFW+4.50+v1.00-FERROX","amp;tr":["udp%3A%2F%2Ftracker.openbittorrent.com%3A80","udp%3A%2F%2Fopen.demonii.com%3A1337","udp%3A%2F%2Ftracker.coppersurfer.tk%3A6969","udp%3A%2F%2Fexodus.desync.com%3A6969"],"infoHash":"5b27f76967b84f0a3d0528a2d1dd0738c8310cf2","infoHashBuffer":{"type":"Buffer","data":[91,39,247,105,103,184,79,10,61,5,40,162,209,221,7,56,200,49,12,242]},"announce":[],"urlList":[]}}