{"title":"Grindhouse.2007.720p.BluRay.x264-SiNN Death Proof, Planet Terror","uid":11777307,"size":8582781578,"categoryP":"video","categoryS":"hd___movies","magnet":"?xt=urn:btih:602d858fcef5ca945398d546774e76ee40c5a69d&amp;dn=Grindhouse.2007.720p.BluRay.x264-SiNN+Death+Proof%2C+Planet+Terror&amp;tr=udp%3A%2F%2Ftracker.openbittorrent.com%3A80&amp;tr=udp%3A%2F%2Fopen.demonii.com%3A1337&amp;tr=udp%3A%2F%2Ftracker.coppersurfer.tk%3A6969&amp;tr=udp%3A%2F%2Fexodus.desync.com%3A6969","seeders":1,"leechers":2,"uploader":"GoodFilms","files":4,"time":1427329562,"description":"Grindhouse.2007.720p.BluRay.x264-SiNNERS\n\nIMDB rating..: 7.7/10 from 141,579 users\n &lt;a href=&quot;\nhttp://www.imdb.com/title/tt0462322/&quot; rel=&quot;nofollow&quot; target=&quot;_NEW&quot;&gt;\nhttp://www.imdb.com/title/tt0462322/&lt;/a&gt;\n\nSource.......: Blu Ray\nVideo specs..: x264 @ 5499 kbps\nAudio specs..: English 5.1\n- --&gt; AC3/448 kbps\n\nSubtitles....: English\nRuntime......: 191 min 13 sec\n\nThis is the theatrical release where Planet Terror and\nDeath Proof were shown as a double-feature along with\nthe &quot;fake&quot; trailers","torrent":{"xt":"urn:btih:602d858fcef5ca945398d546774e76ee40c5a69d","amp;dn":"Grindhouse.2007.720p.BluRay.x264-SiNN+Death+Proof%2C+Planet+Terror","amp;tr":["udp%3A%2F%2Ftracker.openbittorrent.com%3A80","udp%3A%2F%2Fopen.demonii.com%3A1337","udp%3A%2F%2Ftracker.coppersurfer.tk%3A6969","udp%3A%2F%2Fexodus.desync.com%3A6969"],"infoHash":"602d858fcef5ca945398d546774e76ee40c5a69d","infoHashBuffer":{"type":"Buffer","data":[96,45,133,143,206,245,202,148,83,152,213,70,119,78,118,238,64,197,166,157]},"announce":[],"urlList":[]}}