{"title":"Antobal's Cubans - Antobal's Cubans 1932-1937","uid":7287062,"size":68180736,"categoryP":"audio","categoryS":"music","magnet":"?xt=urn:btih:64cf1d4c0be9b44186d7e5072560500ddbba153d&amp;dn=Antobal%27s+Cubans+-+Antobal%27s+Cubans+1932-1937&amp;tr=udp%3A%2F%2Ftracker.openbittorrent.com%3A80&amp;tr=udp%3A%2F%2Fopen.demonii.com%3A1337&amp;tr=udp%3A%2F%2Ftracker.coppersurfer.tk%3A6969&amp;tr=udp%3A%2F%2Fexodus.desync.com%3A6969","seeders":1,"leechers":1,"uploader":"mudmashers","files":18,"time":1337617226,"description":"Antobal's Cubans - Antobal's Cubans 1932-1937 [Harlequin] (LP192kb)\n\t\t\n01. Conga Karabalicero\n02. Les Trois Coups\n03. El Maraquero\n04. Mammy Bong\n05. Cuban Belle\n06. Viene La Conga\n07. Songo Songo\n08. Mulatta Likes The Rumba\n09. Said The Monkey\n10. Let's Be Gay\n11. Cachita\n12. Marianna\n13. Say 'si,Si'\n14. The Moon Over Cuba Was High And So Was I\n15. Whoa! Nellie, Whoa\n16. La Conga\n","torrent":{"xt":"urn:btih:64cf1d4c0be9b44186d7e5072560500ddbba153d","amp;dn":"Antobal%27s+Cubans+-+Antobal%27s+Cubans+1932-1937","amp;tr":["udp%3A%2F%2Ftracker.openbittorrent.com%3A80","udp%3A%2F%2Fopen.demonii.com%3A1337","udp%3A%2F%2Ftracker.coppersurfer.tk%3A6969","udp%3A%2F%2Fexodus.desync.com%3A6969"],"infoHash":"64cf1d4c0be9b44186d7e5072560500ddbba153d","infoHashBuffer":{"type":"Buffer","data":[100,207,29,76,11,233,180,65,134,215,229,7,37,96,80,13,219,186,21,61]},"announce":[],"urlList":[]}}