{"title":"Twisted Coil - One Of Us","uid":7116311,"size":31314450,"categoryP":"audio","categoryS":"music","magnet":"?xt=urn:btih:66ce04303734eea4d9e472fde29cecd50e26a843&amp;dn=Twisted+Coil+-+One+Of+Us&amp;tr=udp%3A%2F%2Ftracker.openbittorrent.com%3A80&amp;tr=udp%3A%2F%2Fopen.demonii.com%3A1337&amp;tr=udp%3A%2F%2Ftracker.coppersurfer.tk%3A6969&amp;tr=udp%3A%2F%2Fexodus.desync.com%3A6969","seeders":1,"leechers":0,"uploader":"Grrhh","files":8,"time":1332228557,"description":"Twisted Coil was a Heavy Metal Band from California.\nI searched many years to get this record, and it was really hard to find, so I decided to put this online. \nIts their first and only record.\nEnjoy.","torrent":{"xt":"urn:btih:66ce04303734eea4d9e472fde29cecd50e26a843","amp;dn":"Twisted+Coil+-+One+Of+Us","amp;tr":["udp%3A%2F%2Ftracker.openbittorrent.com%3A80","udp%3A%2F%2Fopen.demonii.com%3A1337","udp%3A%2F%2Ftracker.coppersurfer.tk%3A6969","udp%3A%2F%2Fexodus.desync.com%3A6969"],"infoHash":"66ce04303734eea4d9e472fde29cecd50e26a843","infoHashBuffer":{"type":"Buffer","data":[102,206,4,48,55,52,238,164,217,228,114,253,226,156,236,213,14,38,168,67]},"announce":[],"urlList":[]}}