{"title":"{DorcelClub}  Ines Lenvin - Nurse Sodomized By Her Patient (03 M","uid":14512919,"size":181461243,"categoryP":"porn","categoryS":"other","magnet":"?xt=urn:btih:6c3579aae4670bf475caa2ecbf05d3ce99028994&amp;dn=%7BDorcelClub%7D++Ines+Lenvin+-+Nurse+Sodomized+By+Her+Patient+%2803+M&amp;tr=udp%3A%2F%2Ftracker.leechers-paradise.org%3A6969&amp;tr=udp%3A%2F%2Fzer0day.ch%3A1337&amp;tr=udp%3A%2F%2Fopen.demonii.com%3A1337&amp;tr=udp%3A%2F%2Ftracker.coppersurfer.tk%3A6969&amp;tr=udp%3A%2F%2Fexodus.desync.com%3A6969","seeders":1,"leechers":0,"uploader":"porn4u","files":1,"time":1462305662,"description":"{DorcelClub}  Ines Lenvin - Nurse Sodomized By Her Patient (03 May 2016) 720p\r\n\r\n\r\n\r\nscreenshot\r\n\r\n \nhttp://imgdone.com/viewer.php?file=55176261191392998626.jpg\r\n\r\n\r\nGeneral info: \r\n\r\n\r\nSize: 173 Mb, \r\nDuration: 00: 11: 32, \r\nStreams: 2, \r\nFull bitrate: 2097 kb/s\r\nVideo: H264 (avc1), 1280x720, 25 fps\r\nAudio: AAC, STEREO, 48 kHz, 92 kb/s\r\n\r\n\r\nIn this scene, the nurse ( Ines Lenvin ) meet her lover, a farmer (played by Mike Angelo). He invites her to have coffee in his kitchen ... but they'll do something else!\r\nHere's an interview of the young French:\r\n&quot;This is the first time I was shooting with Mike, and I understand why he's such a great actor. He was able to find my G-spot very quickly, and I really enjoyed. It was delicious! I love anal sex and his dick is perfectly made for this ... &quot;","torrent":{"xt":"urn:btih:6c3579aae4670bf475caa2ecbf05d3ce99028994","amp;dn":"%7BDorcelClub%7D++Ines+Lenvin+-+Nurse+Sodomized+By+Her+Patient+%2803+M","amp;tr":["udp%3A%2F%2Ftracker.leechers-paradise.org%3A6969","udp%3A%2F%2Fzer0day.ch%3A1337","udp%3A%2F%2Fopen.demonii.com%3A1337","udp%3A%2F%2Ftracker.coppersurfer.tk%3A6969","udp%3A%2F%2Fexodus.desync.com%3A6969"],"infoHash":"6c3579aae4670bf475caa2ecbf05d3ce99028994","infoHashBuffer":{"type":"Buffer","data":[108,53,121,170,228,103,11,244,117,202,162,236,191,5,211,206,153,2,137,148]},"announce":[],"urlList":[]}}