{"title":"The Kings Speech 2011 BRRip XviD Audio Latino-JcGoku21","uid":6550035,"size":838869271,"categoryP":"video","categoryS":"movies","magnet":"?xt=urn:btih:799bb7d7bb1e0dbe96235c491de26b229dda8994&amp;dn=The+Kings+Speech+2011+BRRip+XviD+Audio+Latino-JcGoku21&amp;tr=udp%3A%2F%2Ftracker.openbittorrent.com%3A80&amp;tr=udp%3A%2F%2Fopen.demonii.com%3A1337&amp;tr=udp%3A%2F%2Ftracker.coppersurfer.tk%3A6969&amp;tr=udp%3A%2F%2Fexodus.desync.com%3A6969","seeders":1,"leechers":0,"uploader":"[jcgoku21]","files":3,"time":1311044545,"description":"INFO!!!\n\nVideo Codec....: XviD\nVideo Bitrate..: 827 Kb/s\nAudio Codec....: MP3 CBR\nAudio Bitrate..: 112 Kb/s\nAspect Ratio...: 16:9\nResolution.....: 720 x 400\nFrame Rate.....: 23.976 fps\nRuntime........: 01:58:28\nFile size......: 800 MB\nAudio Language.: Spanish (EspaÃƒÂ±ol Latino)\nSource.........: NTSC.DVD/BRRip.720p.\nEncoder........: JcGoku21\nSubtitles......: N/A\n\nENJOY!!!\n","torrent":{"xt":"urn:btih:799bb7d7bb1e0dbe96235c491de26b229dda8994","amp;dn":"The+Kings+Speech+2011+BRRip+XviD+Audio+Latino-JcGoku21","amp;tr":["udp%3A%2F%2Ftracker.openbittorrent.com%3A80","udp%3A%2F%2Fopen.demonii.com%3A1337","udp%3A%2F%2Ftracker.coppersurfer.tk%3A6969","udp%3A%2F%2Fexodus.desync.com%3A6969"],"infoHash":"799bb7d7bb1e0dbe96235c491de26b229dda8994","infoHashBuffer":{"type":"Buffer","data":[121,155,183,215,187,30,13,190,150,35,92,73,29,226,107,34,157,218,137,148]},"announce":[],"urlList":[]}}