{"title":"Got the Facts on Milk?","uid":8463640,"size":948319964,"categoryP":"video","categoryS":"tv_shows","magnet":"?xt=urn:btih:861b5d44a67a9c81c6a0ea2615b6352177a121c6&amp;dn=Got+the+Facts+on+Milk%3F&amp;tr=udp%3A%2F%2Ftracker.openbittorrent.com%3A80&amp;tr=udp%3A%2F%2Fopen.demonii.com%3A1337&amp;tr=udp%3A%2F%2Ftracker.coppersurfer.tk%3A6969&amp;tr=udp%3A%2F%2Fexodus.desync.com%3A6969","seeders":1,"leechers":0,"uploader":"m_boy","files":-1,"time":1368305926,"description":"A comical fast paced feature documentary, that questions the health benefits of milk and reveals the illuminative powers of major coorparation and the government, promoting the &quot;healthy&quot; dairy product as required unsubstitutable food for children and adults. Featuring various scientific represenatives, this documantary tries to refute one of the oldest and most speculated arguments about the essence of milk.","torrent":{"xt":"urn:btih:861b5d44a67a9c81c6a0ea2615b6352177a121c6","amp;dn":"Got+the+Facts+on+Milk%3F","amp;tr":["udp%3A%2F%2Ftracker.openbittorrent.com%3A80","udp%3A%2F%2Fopen.demonii.com%3A1337","udp%3A%2F%2Ftracker.coppersurfer.tk%3A6969","udp%3A%2F%2Fexodus.desync.com%3A6969"],"infoHash":"861b5d44a67a9c81c6a0ea2615b6352177a121c6","infoHashBuffer":{"type":"Buffer","data":[134,27,93,68,166,122,156,129,198,160,234,38,21,182,53,33,119,161,33,198]},"announce":[],"urlList":[]}}