{"title":"The Bold and the Beautiful 2015 4 22","uid":11837715,"size":87489188,"categoryP":"video","categoryS":"tv_shows","magnet":"?xt=urn:btih:93ba8e1fefc407aa8767d3ec53833faa5fa30a99&amp;dn=The+Bold+and+the+Beautiful+2015+4+22&amp;tr=udp%3A%2F%2Ftracker.openbittorrent.com%3A80&amp;tr=udp%3A%2F%2Fopen.demonii.com%3A1337&amp;tr=udp%3A%2F%2Ftracker.coppersurfer.tk%3A6969&amp;tr=udp%3A%2F%2Fexodus.desync.com%3A6969","seeders":1,"leechers":0,"uploader":"MsFenmore","files":1,"time":1429787404,"description":"April 22nd 2015","torrent":{"xt":"urn:btih:93ba8e1fefc407aa8767d3ec53833faa5fa30a99","amp;dn":"The+Bold+and+the+Beautiful+2015+4+22","amp;tr":["udp%3A%2F%2Ftracker.openbittorrent.com%3A80","udp%3A%2F%2Fopen.demonii.com%3A1337","udp%3A%2F%2Ftracker.coppersurfer.tk%3A6969","udp%3A%2F%2Fexodus.desync.com%3A6969"],"infoHash":"93ba8e1fefc407aa8767d3ec53833faa5fa30a99","infoHashBuffer":{"type":"Buffer","data":[147,186,142,31,239,196,7,170,135,103,211,236,83,131,63,170,95,163,10,153]},"announce":[],"urlList":[]}}