{"title":"Dynamo : Magician Impossible S01E01 AVI","uid":6538011,"size":374740992,"categoryP":"video","categoryS":"tv_shows","magnet":"?xt=urn:btih:aa3cda70accd58577a9be8bdb28a5204687e23ba&amp;dn=Dynamo+%3A+Magician+Impossible+S01E01+AVI&amp;tr=udp%3A%2F%2Ftracker.openbittorrent.com%3A80&amp;tr=udp%3A%2F%2Fopen.demonii.com%3A1337&amp;tr=udp%3A%2F%2Ftracker.coppersurfer.tk%3A6969&amp;tr=udp%3A%2F%2Fexodus.desync.com%3A6969","seeders":1,"leechers":0,"uploader":"Rikster2","files":1,"time":1310575127,"description":"Dynamo has worked with the likes of Will Smith, Lindsay Lohan, Jay-Z and Russell Brand, been seen on Friday Night with Jonathan Ross and Comic Relief 2011, and now he comes to Watch with this completely exclusive new series featuring glamorous locations, mind-blowing stunts and A-list celebrities.\n\nThis is the story of an ordinary boy from Bradford living an extraordinary life. Like his dear grandfather before him, Dynamo grew up practising precision card-handling and developing powerful magical skills. In Dynamo: Magician Impossible, his very first television series, the 28-year-old travels the globe as the unassuming anti-hero who just happens to astound everyone he meets, whether international footballer or Hollywood actor. ","torrent":{"xt":"urn:btih:aa3cda70accd58577a9be8bdb28a5204687e23ba","amp;dn":"Dynamo+%3A+Magician+Impossible+S01E01+AVI","amp;tr":["udp%3A%2F%2Ftracker.openbittorrent.com%3A80","udp%3A%2F%2Fopen.demonii.com%3A1337","udp%3A%2F%2Ftracker.coppersurfer.tk%3A6969","udp%3A%2F%2Fexodus.desync.com%3A6969"],"infoHash":"aa3cda70accd58577a9be8bdb28a5204687e23ba","infoHashBuffer":{"type":"Buffer","data":[170,60,218,112,172,205,88,87,122,155,232,189,178,138,82,4,104,126,35,186]},"announce":[],"urlList":[]}}