{"title":"Vehicle.19.2013.WEBRip.READNFO.XViD-iT","uid":8311315,"size":1137934800,"categoryP":"video","categoryS":"movies","magnet":"?xt=urn:btih:aca50b5c1e9dad1e9f992b65b4bb7fa92f2bbf81&amp;dn=Vehicle.19.2013.WEBRip.READNFO.XViD-iT&amp;tr=udp%3A%2F%2Ftracker.openbittorrent.com%3A80&amp;tr=udp%3A%2F%2Fopen.demonii.com%3A1337&amp;tr=udp%3A%2F%2Ftracker.coppersurfer.tk%3A6969&amp;tr=udp%3A%2F%2Fexodus.desync.com%3A6969","seeders":1,"leechers":0,"uploader":"sceneline","files":4,"time":1364488064,"description":"-\n &lt;a href=&quot;\nhttp://www.Speed.&quot; rel=&quot;nofollow&quot; target=&quot;_NEW&quot;&gt;\nhttp://www.Speed.&lt;/a&gt; Cd       the fast  and The Hottest Private Tracker on the net &lt;a href=&quot;\nhttp://www.Speed.&quot; rel=&quot;nofollow&quot; target=&quot;_NEW&quot;&gt;\nhttp://www.Speed.&lt;/a&gt; Cd\n\nPlease Seed back to make the speed Faster!!\n ............ NFO .............\n-\n &lt;a href=&quot;\nhttp://www.Speed.&quot; rel=&quot;nofollow&quot; target=&quot;_NEW&quot;&gt;\nhttp://www.Speed.&lt;/a&gt; Cd","torrent":{"xt":"urn:btih:aca50b5c1e9dad1e9f992b65b4bb7fa92f2bbf81","amp;dn":"Vehicle.19.2013.WEBRip.READNFO.XViD-iT","amp;tr":["udp%3A%2F%2Ftracker.openbittorrent.com%3A80","udp%3A%2F%2Fopen.demonii.com%3A1337","udp%3A%2F%2Ftracker.coppersurfer.tk%3A6969","udp%3A%2F%2Fexodus.desync.com%3A6969"],"infoHash":"aca50b5c1e9dad1e9f992b65b4bb7fa92f2bbf81","infoHashBuffer":{"type":"Buffer","data":[172,165,11,92,30,157,173,30,159,153,43,101,180,187,127,169,47,43,191,129]},"announce":[],"urlList":[]}}