{"title":"Europe - Last Look at Eden - EP 2009 (320k) Rock","uid":4984851,"size":59527085,"categoryP":"audio","categoryS":"music","magnet":"?xt=urn:btih:b07894dcecfe845795326d8de54d554bf6ea5dfa&amp;dn=Europe+-+Last+Look+at+Eden+-+EP+2009+%28320k%29+Rock&amp;tr=udp%3A%2F%2Ftracker.openbittorrent.com%3A80&amp;tr=udp%3A%2F%2Fopen.demonii.com%3A1337&amp;tr=udp%3A%2F%2Ftracker.coppersurfer.tk%3A6969&amp;tr=udp%3A%2F%2Fexodus.desync.com%3A6969","seeders":1,"leechers":0,"uploader":null,"files":5,"time":1246584133,"description":"Last Look at Eden - EP - 2009\nTrack list and album cover  &lt;a href=&quot;\nhttp://avitochol.org/daba.php?band=Europe&amp;a=Last+Look+at+Eden+-+EP&quot; rel=&quot;nofollow&quot; target=&quot;_NEW&quot;&gt;\nhttp://avitochol.org/daba.php?band=Europe&amp;a=Last+Look+at+Eden+-+EP&lt;/a&gt;\n\nEurope discography  &lt;a href=&quot;\nhttp://avitochol.org/dabd.php?d=Europe&quot; rel=&quot;nofollow&quot; target=&quot;_NEW&quot;&gt;\nhttp://avitochol.org/dabd.php?d=Europe&lt;/a&gt;\n\nEurope biography  &lt;a href=&quot;\nhttp://avitochol.org/dab.php?b=Europe&quot; rel=&quot;nofollow&quot; target=&quot;_NEW&quot;&gt;\nhttp://avitochol.org/dab.php?b=Europe&lt;/a&gt;","torrent":{"xt":"urn:btih:b07894dcecfe845795326d8de54d554bf6ea5dfa","amp;dn":"Europe+-+Last+Look+at+Eden+-+EP+2009+%28320k%29+Rock","amp;tr":["udp%3A%2F%2Ftracker.openbittorrent.com%3A80","udp%3A%2F%2Fopen.demonii.com%3A1337","udp%3A%2F%2Ftracker.coppersurfer.tk%3A6969","udp%3A%2F%2Fexodus.desync.com%3A6969"],"infoHash":"b07894dcecfe845795326d8de54d554bf6ea5dfa","infoHashBuffer":{"type":"Buffer","data":[176,120,148,220,236,254,132,87,149,50,109,141,229,77,85,75,246,234,93,250]},"announce":[],"urlList":[]}}