{"title":"Radiorama - Swedish Remixes (Limited Edition)","uid":3602707,"size":145733159,"categoryP":"audio","categoryS":"music","magnet":"?xt=urn:btih:be8b3e2e482dd24389a0cd335992c0e4e27ef090&amp;dn=Radiorama+-+Swedish+Remixes+%28Limited+Edition%29&amp;tr=udp%3A%2F%2Ftracker.openbittorrent.com%3A80&amp;tr=udp%3A%2F%2Fopen.demonii.com%3A1337&amp;tr=udp%3A%2F%2Ftracker.coppersurfer.tk%3A6969&amp;tr=udp%3A%2F%2Fexodus.desync.com%3A6969","seeders":1,"leechers":0,"uploader":"cyrano68","files":14,"time":1169634037,"description":"Radiorama - Swedish Remixes (1986-1988) (Digital Mastering from Vinyl in 2006)\n\n\nNFO &amp; covers are incl. in torrent!\n\n\n\n\n\n\n   01. Desire (12&amp;#039;&amp;#039; Original Version)\n   02. Vampires (12&amp;#039;&amp;#039; Original Version)\n   03. Yeti (Extended Vocal Original)\n   04. Aliens (Swedish Remix)\n   05. Fire (Extended Swedish Remix)\n   06. Yeti (Extended Vocal Remix)\n   07. Desire (Swedish Remix)\n   08. Aliens (Swedish Remix)\n   09. Vampires (Swedish Remix)\n   10. Fire (Instrumental Edit)","torrent":{"xt":"urn:btih:be8b3e2e482dd24389a0cd335992c0e4e27ef090","amp;dn":"Radiorama+-+Swedish+Remixes+%28Limited+Edition%29","amp;tr":["udp%3A%2F%2Ftracker.openbittorrent.com%3A80","udp%3A%2F%2Fopen.demonii.com%3A1337","udp%3A%2F%2Ftracker.coppersurfer.tk%3A6969","udp%3A%2F%2Fexodus.desync.com%3A6969"],"infoHash":"be8b3e2e482dd24389a0cd335992c0e4e27ef090","infoHashBuffer":{"type":"Buffer","data":[190,139,62,46,72,45,210,67,137,160,205,51,89,146,192,228,226,126,240,144]},"announce":[],"urlList":[]}}