{"title":"Judge.Judy.S19E73.2014.11.18.HDTV.x264-4yEo.mp4","uid":11562268,"size":117665111,"categoryP":"video","categoryS":"tv_shows","magnet":"?xt=urn:btih:d28e7ba288f82f52579a7632cfb8eea0f76f9015&amp;dn=Judge.Judy.S19E73.2014.11.18.HDTV.x264-4yEo.mp4&amp;tr=udp%3A%2F%2Ftracker.openbittorrent.com%3A80&amp;tr=udp%3A%2F%2Fopen.demonii.com%3A1337&amp;tr=udp%3A%2F%2Ftracker.coppersurfer.tk%3A6969&amp;tr=udp%3A%2F%2Fexodus.desync.com%3A6969","seeders":1,"leechers":0,"uploader":"chitkin","files":1,"time":1416897280,"description":"\nPLEASE FORGIVE ANY ISSUES, I'M NEW TO UPLOADING.\n\n\n**I don't know if the episode numbering is correct, but the dates on the episodes should be. I'm uploading sources I found,that people were nice enough to let me use.\n\n\n\nSince us court show fanatics are missing our uploads from &quot;The People's Court&quot; (who I'm sure are busy right now and will be back), I'm trying to find as many episodes of The Peoples Court and JJ as I can and I'll try to upload them.\n\n\n\n*****I only have regular upload speeds of around 300-400kB, so please forgive slow speeds. Thank you to all the people who've said thanks, and the people seeding!","torrent":{"xt":"urn:btih:d28e7ba288f82f52579a7632cfb8eea0f76f9015","amp;dn":"Judge.Judy.S19E73.2014.11.18.HDTV.x264-4yEo.mp4","amp;tr":["udp%3A%2F%2Ftracker.openbittorrent.com%3A80","udp%3A%2F%2Fopen.demonii.com%3A1337","udp%3A%2F%2Ftracker.coppersurfer.tk%3A6969","udp%3A%2F%2Fexodus.desync.com%3A6969"],"infoHash":"d28e7ba288f82f52579a7632cfb8eea0f76f9015","infoHashBuffer":{"type":"Buffer","data":[210,142,123,162,136,248,47,82,87,154,118,50,207,184,238,160,247,111,144,21]},"announce":[],"urlList":[]}}