{"title":"TeensDoPorn - Never Done This Before - Kylie Kane [720p].mp4","uid":8809752,"size":1410330529,"categoryP":"porn","categoryS":"hd___movies","magnet":"?xt=urn:btih:defae705d75f749a0ffbbed658ca8f667b89d84a&amp;dn=TeensDoPorn+-+Never+Done+This+Before+-+Kylie+Kane+%5B720p%5D.mp4&amp;tr=udp%3A%2F%2Ftracker.openbittorrent.com%3A80&amp;tr=udp%3A%2F%2Fopen.demonii.com%3A1337&amp;tr=udp%3A%2F%2Ftracker.coppersurfer.tk%3A6969&amp;tr=udp%3A%2F%2Fexodus.desync.com%3A6969","seeders":1,"leechers":1,"uploader":"C3Porno","files":-1,"time":1376429428,"description":"TeensDoPorn - Never Done This Before - Kylie Kane [720p].mp4\n\n2013, Interview, All sex, Oral, Natural tits, Cumshot, Hardcore, HD, XXX, Adult\n\n1280 x 720\n\n00:36:38\n\n1.31 GB\n\nScreens\n &lt;a href=&quot;\nhttp://www.euro-pic.eu/share-C2B5_520A890A.html&quot; rel=&quot;nofollow&quot; target=&quot;_NEW&quot;&gt;\nhttp://www.euro-pic.eu/share-C2B5_520A890A.html&lt;/a&gt;\n &lt;a href=&quot;\nhttp://www.euro-pic.eu/share-CC31_520A890A.html&quot; rel=&quot;nofollow&quot; target=&quot;_NEW&quot;&gt;\nhttp://www.euro-pic.eu/share-CC31_520A890A.html&lt;/a&gt;\n &lt;a href=&quot;\nhttp://www.euro-pic.eu/share-AECD_520A890A.html&quot; rel=&quot;nofollow&quot; target=&quot;_NEW&quot;&gt;\nhttp://www.euro-pic.eu/share-AECD_520A890A.html&lt;/a&gt;\n &lt;a href=&quot;\nhttp://www.euro-pic.eu/share-6DF0_520A890A.html&quot; rel=&quot;nofollow&quot; target=&quot;_NEW&quot;&gt;\nhttp://www.euro-pic.eu/share-6DF0_520A890A.html&lt;/a&gt;\n &lt;a href=&quot;\nhttp://www.euro-pic.eu/share-4FBC_520A890A.html&quot; rel=&quot;nofollow&quot; target=&quot;_NEW&quot;&gt;\nhttp://www.euro-pic.eu/share-4FBC_520A890A.html&lt;/a&gt;","torrent":{"xt":"urn:btih:defae705d75f749a0ffbbed658ca8f667b89d84a","amp;dn":"TeensDoPorn+-+Never+Done+This+Before+-+Kylie+Kane+%5B720p%5D.mp4","amp;tr":["udp%3A%2F%2Ftracker.openbittorrent.com%3A80","udp%3A%2F%2Fopen.demonii.com%3A1337","udp%3A%2F%2Ftracker.coppersurfer.tk%3A6969","udp%3A%2F%2Fexodus.desync.com%3A6969"],"infoHash":"defae705d75f749a0ffbbed658ca8f667b89d84a","infoHashBuffer":{"type":"Buffer","data":[222,250,231,5,215,95,116,154,15,251,190,214,88,202,143,102,123,137,216,74]},"announce":[],"urlList":[]}}