{"title":"FakeHospital.Gorgeous.Blonde.Sales.Rep.Has.A.Unique.Selling.Tech","uid":9588245,"size":992198604,"categoryP":"porn","categoryS":"other","magnet":"?xt=urn:btih:e298954830d92547f0e1ac659e3055064eac1e17&amp;dn=FakeHospital.Gorgeous.Blonde.Sales.Rep.Has.A.Unique.Selling.Tech&amp;tr=udp%3A%2F%2Ftracker.openbittorrent.com%3A80&amp;tr=udp%3A%2F%2Fopen.demonii.com%3A1337&amp;tr=udp%3A%2F%2Ftracker.coppersurfer.tk%3A6969&amp;tr=udp%3A%2F%2Fexodus.desync.com%3A6969","seeders":1,"leechers":1,"uploader":"makintos13","files":4,"time":1391855184,"description":"SCREENS:\n\n &lt;a href=&quot;\nhttp://shootimg.biz/img-52f5f742c23c8.html&quot; rel=&quot;nofollow&quot; target=&quot;_NEW&quot;&gt;\nhttp://shootimg.biz/img-52f5f742c23c8.html&lt;/a&gt; ","torrent":{"xt":"urn:btih:e298954830d92547f0e1ac659e3055064eac1e17","amp;dn":"FakeHospital.Gorgeous.Blonde.Sales.Rep.Has.A.Unique.Selling.Tech","amp;tr":["udp%3A%2F%2Ftracker.openbittorrent.com%3A80","udp%3A%2F%2Fopen.demonii.com%3A1337","udp%3A%2F%2Ftracker.coppersurfer.tk%3A6969","udp%3A%2F%2Fexodus.desync.com%3A6969"],"infoHash":"e298954830d92547f0e1ac659e3055064eac1e17","infoHashBuffer":{"type":"Buffer","data":[226,152,149,72,48,217,37,71,240,225,172,101,158,48,85,6,78,172,30,23]},"announce":[],"urlList":[]}}