{"title":"Snowpiercer.2013.BRRip.XViD.AC3.ReLeNTLesS","uid":9810453,"size":1290716564,"categoryP":"video","categoryS":"movies","magnet":"?xt=urn:btih:e40a823a1952d07927cf7dbbf9324383c7acee0d&amp;dn=Snowpiercer.2013.BRRip.XViD.AC3.ReLeNTLesS&amp;tr=udp%3A%2F%2Ftracker.openbittorrent.com%3A80&amp;tr=udp%3A%2F%2Fopen.demonii.com%3A1337&amp;tr=udp%3A%2F%2Ftracker.coppersurfer.tk%3A6969&amp;tr=udp%3A%2F%2Fexodus.desync.com%3A6969","seeders":1,"leechers":0,"uploader":"TvTeam","files":5,"time":1395515373,"description":"::::::::::::::::::::::::::::::::::::::::::::::::::::::::::::::::::::::::::\n  &lt;a href=&quot;\nhttp://www.torrenting.com&quot; rel=&quot;nofollow&quot; target=&quot;_NEW&quot;&gt;\nhttp://www.torrenting.com&lt;/a&gt; \n\nExperiance the SPEED of a real Scene Torrent Site !!!\n\n::::::::::::::::::::::::::::::::::::::::::::::::::::::::::::::::::::::::::\n\n(((((((((((((= Enjoy No RAR releases =))))))))))))))))))))","torrent":{"xt":"urn:btih:e40a823a1952d07927cf7dbbf9324383c7acee0d","amp;dn":"Snowpiercer.2013.BRRip.XViD.AC3.ReLeNTLesS","amp;tr":["udp%3A%2F%2Ftracker.openbittorrent.com%3A80","udp%3A%2F%2Fopen.demonii.com%3A1337","udp%3A%2F%2Ftracker.coppersurfer.tk%3A6969","udp%3A%2F%2Fexodus.desync.com%3A6969"],"infoHash":"e40a823a1952d07927cf7dbbf9324383c7acee0d","infoHashBuffer":{"type":"Buffer","data":[228,10,130,58,25,82,208,121,39,207,125,187,249,50,67,131,199,172,238,13]},"announce":[],"urlList":[]}}