{"title":"Jay.Leno.2013.04.25.Gwyneth.Paltrow.HDTV.XviD-AFG","uid":8412953,"size":885218656,"categoryP":"video","categoryS":"tv_shows","magnet":"?xt=urn:btih:e55fd5f011e38996ebd1caf09c3e80f7d237ddfe&amp;dn=Jay.Leno.2013.04.25.Gwyneth.Paltrow.HDTV.XviD-AFG&amp;tr=udp%3A%2F%2Ftracker.openbittorrent.com%3A80&amp;tr=udp%3A%2F%2Fopen.demonii.com%3A1337&amp;tr=udp%3A%2F%2Ftracker.coppersurfer.tk%3A6969&amp;tr=udp%3A%2F%2Fexodus.desync.com%3A6969","seeders":1,"leechers":0,"uploader":"TvTeam","files":4,"time":1366963948,"description":"::::::::::::::::::::::::::::::::::::::::::::::::::::::::::::::::::::::::::\n  &lt;a href=&quot;\nhttp://www.torrenting.com&quot; rel=&quot;nofollow&quot; target=&quot;_NEW&quot;&gt;\nhttp://www.torrenting.com&lt;/a&gt;\n\n::::::::::::::::::::::::::::::::::::::::::::::::::::::::::::::::::::::::::\n\n(((((((((((((= Enjoy No RAR releases =))))))))))))))))))))\n\n\nMust Try:  &lt;a href=&quot; http://www.torrenting.com&quot; rel=&quot;nofollow&quot; target=&quot;_NEW&quot;&gt; http://www.torrenting.com&lt;/a&gt;","torrent":{"xt":"urn:btih:e55fd5f011e38996ebd1caf09c3e80f7d237ddfe","amp;dn":"Jay.Leno.2013.04.25.Gwyneth.Paltrow.HDTV.XviD-AFG","amp;tr":["udp%3A%2F%2Ftracker.openbittorrent.com%3A80","udp%3A%2F%2Fopen.demonii.com%3A1337","udp%3A%2F%2Ftracker.coppersurfer.tk%3A6969","udp%3A%2F%2Fexodus.desync.com%3A6969"],"infoHash":"e55fd5f011e38996ebd1caf09c3e80f7d237ddfe","infoHashBuffer":{"type":"Buffer","data":[229,95,213,240,17,227,137,150,235,209,202,240,156,62,128,247,210,55,221,254]},"announce":[],"urlList":[]}}