{"title":"Mozart. Piano Concertos 17 &amp; 20 (Leif Ove Andsnes, 2008)","uid":12752405,"size":209164121,"categoryP":"audio","categoryS":"flac","magnet":"?xt=urn:btih:f5421a72e77e48be4b63811b195c515cbf52b5c9&amp;dn=Mozart.+Piano+Concertos+17+%26amp%3B+20+%28Leif+Ove+Andsnes%2C+2008%29&amp;tr=udp%3A%2F%2Ftracker.leechers-paradise.org%3A6969&amp;tr=udp%3A%2F%2Fzer0day.ch%3A1337&amp;tr=udp%3A%2F%2Fopen.demonii.com%3A1337&amp;tr=udp%3A%2F%2Ftracker.coppersurfer.tk%3A6969&amp;tr=udp%3A%2F%2Fexodus.desync.com%3A6969","seeders":1,"leechers":0,"uploader":null,"files":11,"time":1447397271,"description":"Genre: Classical\r\nOrigin: UK\r\nFormat: FLAC, tracks+.cue\r\nTT: 00h57'59&quot;\r\n\r\nPiano Concerto № 17 G-Dur K 452\r\n01. I. Allegro [11'34&quot;]\r\n02. II. Andante [09'20&quot;]\r\n03. III. Allegretto [07'19&quot;]\r\n\r\nPiano Concerto № 20 d-mpll K 466\r\n04. I. Allegro [14'00&quot;]\r\n05. II. Romanze [08'19&quot;]\r\n06. III. Rondeau: Allegro Assai [07'27&quot;]\r\n\r\nNorwegian Chamber Orchestra, cond. Leif Ove Andsnes, Piano – Leif Ove Andsnes","torrent":{"xt":"urn:btih:f5421a72e77e48be4b63811b195c515cbf52b5c9","amp;dn":"Mozart.+Piano+Concertos+17+%26amp%3B+20+%28Leif+Ove+Andsnes%2C+2008%29","amp;tr":["udp%3A%2F%2Ftracker.leechers-paradise.org%3A6969","udp%3A%2F%2Fzer0day.ch%3A1337","udp%3A%2F%2Fopen.demonii.com%3A1337","udp%3A%2F%2Ftracker.coppersurfer.tk%3A6969","udp%3A%2F%2Fexodus.desync.com%3A6969"],"infoHash":"f5421a72e77e48be4b63811b195c515cbf52b5c9","infoHashBuffer":{"type":"Buffer","data":[245,66,26,114,231,126,72,190,75,99,129,27,25,92,81,92,191,82,181,201]},"announce":[],"urlList":[]}}